jwt_postgresql_proxy.py
jwt_postgresql_proxy-0.0.2.dist-info/METADATA
jwt_postgresql_proxy-0.0.2.dist-info/WHEEL
jwt_postgresql_proxy-0.0.2.dist-info/entry_points.txt
jwt_postgresql_proxy-0.0.2.dist-info/top_level.txt
jwt_postgresql_proxy-0.0.2.dist-info/RECORD
