Metadata-Version: 2.1
Name: jwt-postgresql-proxy
Version: 0.0.2
Summary: Stateless JWT authentication in front of PostgreSQL
Home-page: https://github.com/uktrade/jwt-postgresql-proxy
Author: Department for International Trade
Author-email: webops@digital.trade.gov.uk
License: UNKNOWN
Platform: UNKNOWN
Classifier: Programming Language :: Python :: 3
Classifier: License :: OSI Approved :: MIT License
Requires-Python: >=3.8.0
Requires-Dist: cryptography (>=3.3.1)
Requires-Dist: gevent (>=20.12.1)
